{
    "schemaVersion": 2,
    "mediaType": "application/vnd.docker.distribution.manifest.v2+json",
    "config": {
        "mediaType": "application/vnd.docker.container.image.v1+json",
        "size": 1869,
        "digest": "sha256:3baf7810b525bad3991d8c1fc6824561e7f2a0592dfffbe54cc8329efd973bab"
    },
    "layers": [
        {
            "mediaType": "application/vnd.docker.image.rootfs.diff.tar.gzip",
            "size": 92,
            "digest": "sha256:a9b5642346864812b493226d322a3138bb05a54a3187326174936a67fd141992"
        },
        {
            "mediaType": "application/vnd.docker.image.rootfs.diff.tar.gzip",
            "size": 9660180,
            "digest": "sha256:83bb49be56bac43c90daed7fcae9c40581768b0273e771cadc9b9dcc6692d44f"
        }
    ]
}