{
    "schemaVersion": 2,
    "mediaType": "application/vnd.docker.distribution.manifest.v2+json",
    "config": {
        "mediaType": "application/vnd.docker.container.image.v1+json",
        "size": 2068,
        "digest": "sha256:c16ea08edad878c69fdb14a861f32bff33d40e302457fbaa4b8f89c6a5b5f8bc"
    },
    "layers": [
        {
            "mediaType": "application/vnd.docker.image.rootfs.diff.tar.gzip",
            "size": 140200,
            "digest": "sha256:2af7101bd3c309dd14fa9acd1f24031d7fe322a3eafc81280e84beff842ee12e"
        },
        {
            "mediaType": "application/vnd.docker.image.rootfs.diff.tar.gzip",
            "size": 92,
            "digest": "sha256:f6c94b28bf016b738cba7cb3323043c49bbd6a838dd1b9d0f358437e55b70586"
        },
        {
            "mediaType": "application/vnd.docker.image.rootfs.diff.tar.gzip",
            "size": 12898290,
            "digest": "sha256:3fbc2898b2120684beeba0941c5e64a212361a82e299ffe37b6c6d29d1d8170a"
        }
    ]
}