{
    "schemaVersion": 2,
    "mediaType": "application/vnd.docker.distribution.manifest.v2+json",
    "config": {
        "mediaType": "application/vnd.docker.container.image.v1+json",
        "size": 2277,
        "digest": "sha256:64b53f03d05e22ca27c774b0a0dc8131c031116439495d1b26e72bca05ec5017"
    },
    "layers": [
        {
            "mediaType": "application/vnd.docker.image.rootfs.diff.tar.gzip",
            "size": 654467,
            "digest": "sha256:e8d8785a314f385d3675a017f4e2df1707c528c06e7a7989663fdab4900bd8ff"
        },
        {
            "mediaType": "application/vnd.docker.image.rootfs.diff.tar.gzip",
            "size": 25216878,
            "digest": "sha256:ed1619a7ca2f147a50f64011e25e2f35292b45130ac460f624ce2e8b873945e1"
        },
        {
            "mediaType": "application/vnd.docker.image.rootfs.diff.tar.gzip",
            "size": 121463,
            "digest": "sha256:5118d1c35593fea382e9e14d538441dd8191d79e8b670d0be6f6d820c7df1ecc"
        },
        {
            "mediaType": "application/vnd.docker.image.rootfs.diff.tar.gzip",
            "size": 152269,
            "digest": "sha256:801a2002a998f223b11222cc50a5ecc0410ad437e1165b929c5cdd3f7beac033"
        }
    ]
}