{
    "schemaVersion": 2,
    "mediaType": "application/vnd.docker.distribution.manifest.v2+json",
    "config": {
        "mediaType": "application/vnd.docker.container.image.v1+json",
        "size": 2652,
        "digest": "sha256:042667acc0f81cd1f285555f886e58631c513248270ba62e34934126b3153313"
    },
    "layers": [
        {
            "mediaType": "application/vnd.docker.image.rootfs.diff.tar.gzip",
            "size": 126,
            "digest": "sha256:1075bb48018e7fffb4e37aeca6f56ba6e6f8de1b506bc445b1dae81e1eeeea85"
        },
        {
            "mediaType": "application/vnd.docker.image.rootfs.diff.tar.gzip",
            "size": 5247303,
            "digest": "sha256:5d8b7c63e6e9a7cbcab2f2f703a94680b9c5d839fe7be26e5790361053514a20"
        },
        {
            "mediaType": "application/vnd.docker.image.rootfs.diff.tar.gzip",
            "size": 531160,
            "digest": "sha256:d3da53ab4c9c3b99cfa69133bb62ffb277f44c890563fb370b052416eac3181c"
        },
        {
            "mediaType": "application/vnd.docker.image.rootfs.diff.tar.gzip",
            "size": 3805,
            "digest": "sha256:70b62c1c27a8202b4cfb1adf8d90b4133502d9ab281ff673d3b5de331246b394"
        },
        {
            "mediaType": "application/vnd.docker.image.rootfs.diff.tar.gzip",
            "size": 97635,
            "digest": "sha256:8661e31d6854ee8c5630e621a7167dfd07d77ad4c0904279e32c50b4bde054ef"
        }
    ]
}