{
    "schemaVersion": 2,
    "mediaType": "application/vnd.docker.distribution.manifest.v2+json",
    "config": {
        "mediaType": "application/vnd.docker.container.image.v1+json",
        "size": 2652,
        "digest": "sha256:9a53b4ff8aa08a2223bb1432efd94ba3856370ca733c5f22e36c0b866c25484d"
    },
    "layers": [
        {
            "mediaType": "application/vnd.docker.image.rootfs.diff.tar.gzip",
            "size": 126,
            "digest": "sha256:6ed7af34b09e713d52571f10c54a4660c642a533f51293fa097ac4c0432867e5"
        },
        {
            "mediaType": "application/vnd.docker.image.rootfs.diff.tar.gzip",
            "size": 3266339,
            "digest": "sha256:78c5ea43664f2da00ffc09a47cf126c60c21378b08ecf3477f72fdcdb01d45ee"
        },
        {
            "mediaType": "application/vnd.docker.image.rootfs.diff.tar.gzip",
            "size": 531159,
            "digest": "sha256:ef484489b1e109fcb52604f7f23a3846fbf6fd389f8a075774b744775f630bc0"
        },
        {
            "mediaType": "application/vnd.docker.image.rootfs.diff.tar.gzip",
            "size": 3803,
            "digest": "sha256:5a11e014b0b79d152ba07c9b466d9b860727259cda1ec6290ac60235b17f25fd"
        },
        {
            "mediaType": "application/vnd.docker.image.rootfs.diff.tar.gzip",
            "size": 105939,
            "digest": "sha256:e698ec12da232dbfdd04401c09235d13990d1befe43d057caa74c424ff92db50"
        }
    ]
}