{
    "schemaVersion": 2,
    "mediaType": "application/vnd.docker.distribution.manifest.list.v2+json",
    "manifests": [
        {
            "mediaType": "application/vnd.docker.distribution.manifest.v2+json",
            "size": 741,
            "digest": "sha256:d8bfa132b74468fc3331ecce3e18b5c56c7811f81302782ec8c741154e42fd31",
            "platform": {
                "architecture": "amd64",
                "os": "linux"
            }
        },
        {
            "mediaType": "application/vnd.docker.distribution.manifest.v2+json",
            "size": 741,
            "digest": "sha256:c8c645c08d08fbb0dd13252c08ecbf7ea85d554796f028b664b9cedecfd3415a",
            "platform": {
                "architecture": "arm",
                "os": "linux"
            }
        },
        {
            "mediaType": "application/vnd.docker.distribution.manifest.v2+json",
            "size": 741,
            "digest": "sha256:5226d69187cced7e8ec8f3bf0ae38db0dd3f22cecf397008c4d70f2368658b2c",
            "platform": {
                "architecture": "arm64",
                "os": "linux"
            }
        },
        {
            "mediaType": "application/vnd.docker.distribution.manifest.v2+json",
            "size": 741,
            "digest": "sha256:97b5f9169de7a19adaf228f34382e8d0446953072f14d1f4cd61d6fa4c6a270a",
            "platform": {
                "architecture": "ppc64le",
                "os": "linux"
            }
        },
        {
            "mediaType": "application/vnd.docker.distribution.manifest.v2+json",
            "size": 741,
            "digest": "sha256:184b72b618c2329a7a1882e3a4b0b804d9cd90356e67cc1ec741e7eb43a66190",
            "platform": {
                "architecture": "s390x",
                "os": "linux"
            }
        }
    ]
}