{
    "schemaVersion": 2,
    "mediaType": "application/vnd.docker.distribution.manifest.v2+json",
    "config": {
        "mediaType": "application/vnd.docker.container.image.v1+json",
        "size": 1602,
        "digest": "sha256:cbdbf604bb7586e870ed575509f4c35d2babed7821084d2b0f3d9d8b5439c3e2"
    },
    "layers": [
        {
            "mediaType": "application/vnd.docker.image.rootfs.diff.tar.gzip",
            "size": 7689429,
            "digest": "sha256:8f125ded1b483229a567e48eece98cc8867c2bee55fb73e9cd65ceecc448b7c7"
        },
        {
            "mediaType": "application/vnd.docker.image.rootfs.diff.tar.gzip",
            "size": 98,
            "digest": "sha256:4003b5b92ca98a8926d9112839f3f17e69f4ec4f995abb188a3ce3ccf93cd6d9"
        },
        {
            "mediaType": "application/vnd.docker.image.rootfs.diff.tar.gzip",
            "size": 12373019,
            "digest": "sha256:76332c49c7d1089fbfa339ad06285ccaa87d46e159413817ca47ec6ed9ba74a0"
        }
    ]
}