{
    "schemaVersion": 2,
    "mediaType": "application/vnd.docker.distribution.manifest.v2+json",
    "config": {
        "mediaType": "application/vnd.docker.container.image.v1+json",
        "size": 2598,
        "digest": "sha256:873c4a84b19e6a40d6871c9a0d52b54b2bf7053ee057fb11b3ffe907b260deac"
    },
    "layers": [
        {
            "mediaType": "application/vnd.docker.image.rootfs.diff.tar.gzip",
            "size": 27098756,
            "digest": "sha256:afb6ec6fdc1c3ba04f7a56db32c5ff5ff38962dc4cd0ffdef5beaa0ce2eb77e2"
        },
        {
            "mediaType": "application/vnd.docker.image.rootfs.diff.tar.gzip",
            "size": 667,
            "digest": "sha256:9426851c617d51b07e12d0b33f92d21edfec2b6b97caef936172ba7b61148ff5"
        },
        {
            "mediaType": "application/vnd.docker.image.rootfs.diff.tar.gzip",
            "size": 4710,
            "digest": "sha256:ee229040374083b5aad60f6de0ef9c7e98783ab7594f91b6c5728473e7e21994"
        },
        {
            "mediaType": "application/vnd.docker.image.rootfs.diff.tar.gzip",
            "size": 12130326,
            "digest": "sha256:a9b500600e94729f859a15994ec516daa6f3a807727e3eb145bad7e30014c4e8"
        },
        {
            "mediaType": "application/vnd.docker.image.rootfs.diff.tar.gzip",
            "size": 703,
            "digest": "sha256:9fd7be8b144b5bee94491fe07561ff1d33ba09295cc51b855125e8668ca2d8b0"
        },
        {
            "mediaType": "application/vnd.docker.image.rootfs.diff.tar.gzip",
            "size": 268313,
            "digest": "sha256:fb6ba7e6e1d0ee47e9c09c1d06e6d3668fb5b1788c79718b12cd32340b770896"
        },
        {
            "mediaType": "application/vnd.docker.image.rootfs.diff.tar.gzip",
            "size": 1368,
            "digest": "sha256:b0be49ac942edecab27309765452f7496d343d725c3dc3abb9f6d0d415396402"
        },
        {
            "mediaType": "application/vnd.docker.image.rootfs.diff.tar.gzip",
            "size": 132435,
            "digest": "sha256:3df46c422400bbf5e9b89cd95a2b4f0319fb044dba9bc88f02f405132dcd6bfd"
        }
    ]
}