{
    "schemaVersion": 2,
    "mediaType": "application/vnd.docker.distribution.manifest.v2+json",
    "config": {
        "mediaType": "application/vnd.docker.container.image.v1+json",
        "size": 2839,
        "digest": "sha256:b02d36603babc75a1d5372597f00df469357ef429aaee2a34d36d77e705a62f3"
    },
    "layers": [
        {
            "mediaType": "application/vnd.docker.image.rootfs.diff.tar.gzip",
            "size": 2802957,
            "digest": "sha256:c9b1b535fdd91a9855fb7f82348177e5f019329a58c53c47272962dd60f71fc9"
        },
        {
            "mediaType": "application/vnd.docker.image.rootfs.diff.tar.gzip",
            "size": 91813354,
            "digest": "sha256:6829f95944234e6416ba25a4682685a81367677ab83f36be29e092e0d14ba991"
        },
        {
            "mediaType": "application/vnd.docker.image.rootfs.diff.tar.gzip",
            "size": 64688770,
            "digest": "sha256:5fff7de586a68688986c7af8dbec113482ca0f781c7859e3e7eaba383d44c631"
        },
        {
            "mediaType": "application/vnd.docker.image.rootfs.diff.tar.gzip",
            "size": 1267,
            "digest": "sha256:c09ddccb1b4d21547ea7cd4b97ac6f967d835d4e5767805916f6d120e29a10e3"
        }
    ]
}