{
    "schemaVersion": 2,
    "mediaType": "application/vnd.docker.distribution.manifest.v2+json",
    "config": {
        "mediaType": "application/vnd.docker.container.image.v1+json",
        "size": 3049,
        "digest": "sha256:60bda6b22090512e6f6a7a81854414684d8b6db6550548d0aa17e2e1ee9c25fe"
    },
    "layers": [
        {
            "mediaType": "application/vnd.docker.image.rootfs.diff.tar.gzip",
            "size": 2813316,
            "digest": "sha256:cbdbe7a5bc2a134ca8ec91be58565ec07d037386d1f1d8385412d224deafca08"
        },
        {
            "mediaType": "application/vnd.docker.image.rootfs.diff.tar.gzip",
            "size": 94568992,
            "digest": "sha256:5794ddd03c4b75eb801a7d9310dc7dec17b1179685a91f51700dad228ac1ebd5"
        },
        {
            "mediaType": "application/vnd.docker.image.rootfs.diff.tar.gzip",
            "size": 64258327,
            "digest": "sha256:ada38400ea57c6e0ac0331004a47316bb3408ea3a753c0979d3d306656e8e2f6"
        },
        {
            "mediaType": "application/vnd.docker.image.rootfs.diff.tar.gzip",
            "size": 1264,
            "digest": "sha256:f5aefdd031ae62115280d75d7c3e823d34bffc343c858a5a93c50d4e76e30613"
        },
        {
            "mediaType": "application/vnd.docker.image.rootfs.diff.tar.gzip",
            "size": 178,
            "digest": "sha256:ac906854dbe4332a6e976d4beb6c9fd43db11c15d26d4ace6c26c6a76a2efb32"
        }
    ]
}