{
    "schemaVersion": 2,
    "mediaType": "application/vnd.docker.distribution.manifest.v2+json",
    "config": {
        "mediaType": "application/vnd.docker.container.image.v1+json",
        "size": 5054,
        "digest": "sha256:401764c6f50f94c07e0a17664a85ac947d89e5b96b193d1650aaffcfe232d78d"
    },
    "layers": [
        {
            "mediaType": "application/vnd.docker.image.rootfs.diff.tar.gzip",
            "size": 2802957,
            "digest": "sha256:c9b1b535fdd91a9855fb7f82348177e5f019329a58c53c47272962dd60f71fc9"
        },
        {
            "mediaType": "application/vnd.docker.image.rootfs.diff.tar.gzip",
            "size": 62027714,
            "digest": "sha256:4e2af10642877574321c10386d2248bf7a1f50bd8b40f7991d77df3286c1f972"
        },
        {
            "mediaType": "application/vnd.docker.image.rootfs.diff.tar.gzip",
            "size": 11665,
            "digest": "sha256:6450f42c2c93c190ef68ef351f7eb414fd600cfb894b518092f637732929cb0c"
        },
        {
            "mediaType": "application/vnd.docker.image.rootfs.diff.tar.gzip",
            "size": 8088,
            "digest": "sha256:5cc18f9c91c58d2aa60b593aa6ae872f78ea8b5164f9c54119a022947d1e8a5a"
        },
        {
            "mediaType": "application/vnd.docker.image.rootfs.diff.tar.gzip",
            "size": 129,
            "digest": "sha256:dbefa74a7157877e43ad3a8cb4b0bfe7fdcc104d99d1919130259a53952d61f5"
        },
        {
            "mediaType": "application/vnd.docker.image.rootfs.diff.tar.gzip",
            "size": 101031855,
            "digest": "sha256:53e15ff702a7485a52f9c063984265616111fe43eb18787ac0d216b29a99f4a3"
        },
        {
            "mediaType": "application/vnd.docker.image.rootfs.diff.tar.gzip",
            "size": 25480559,
            "digest": "sha256:15721726dd868ecd4858fd88db476cd1cfee295923ba8082556bc3dc620f2589"
        },
        {
            "mediaType": "application/vnd.docker.image.rootfs.diff.tar.gzip",
            "size": 8389157,
            "digest": "sha256:1cf7de84a4716c3d36b10eb46c995d1e29168eb95ee903f9c28e7e363595d9a4"
        },
        {
            "mediaType": "application/vnd.docker.image.rootfs.diff.tar.gzip",
            "size": 1268,
            "digest": "sha256:38d0b986b357619c1e2a2e146367e31a26c7248a8e3704dd7bfc02ce0b54f96a"
        }
    ]
}