{
    "schemaVersion": 2,
    "mediaType": "application/vnd.docker.distribution.manifest.v2+json",
    "config": {
        "mediaType": "application/vnd.docker.container.image.v1+json",
        "size": 5056,
        "digest": "sha256:8e2e01aa7a261c2e64181af711750f43b84ca19c187c85edb568b876e9064e37"
    },
    "layers": [
        {
            "mediaType": "application/vnd.docker.image.rootfs.diff.tar.gzip",
            "size": 2801778,
            "digest": "sha256:e6b0cf9c0882fb079c9d35361d12ff4691f916b6d825061247d1bd0b26d7cf3f"
        },
        {
            "mediaType": "application/vnd.docker.image.rootfs.diff.tar.gzip",
            "size": 60483562,
            "digest": "sha256:7fd587908686672a25e4a7266743e11df267699f1eb541a0964990ccd36ec746"
        },
        {
            "mediaType": "application/vnd.docker.image.rootfs.diff.tar.gzip",
            "size": 11663,
            "digest": "sha256:de6c6395ea49ea773fa51f71b763bf274dfb1d09ba0cd64bbbc64de87c8fa724"
        },
        {
            "mediaType": "application/vnd.docker.image.rootfs.diff.tar.gzip",
            "size": 8087,
            "digest": "sha256:19abdc5548de3074e1914af264008dd76c0531a2f3470f767ac427ed051d87fd"
        },
        {
            "mediaType": "application/vnd.docker.image.rootfs.diff.tar.gzip",
            "size": 129,
            "digest": "sha256:741a8ce4cca8bba63591da0b92944890da214792f4b0677b025538555983b94b"
        },
        {
            "mediaType": "application/vnd.docker.image.rootfs.diff.tar.gzip",
            "size": 101000624,
            "digest": "sha256:bc3f9f6f52838599dd02b243fa521c510ad70cd59ba67a24cacc4849a5040b1d"
        },
        {
            "mediaType": "application/vnd.docker.image.rootfs.diff.tar.gzip",
            "size": 25480554,
            "digest": "sha256:26269ac0633c988026d6cec601c784b1dccac43be5b551ca162184cb30fd05cc"
        },
        {
            "mediaType": "application/vnd.docker.image.rootfs.diff.tar.gzip",
            "size": 8389150,
            "digest": "sha256:05d492680e693aa5f90987699d658b7000b32810c5baccc6f2ee4d80e3dcf91a"
        },
        {
            "mediaType": "application/vnd.docker.image.rootfs.diff.tar.gzip",
            "size": 1261,
            "digest": "sha256:5477d66b6e25b245badd515583e1637bb8f6a715be8db7e7d2b59cf797170a93"
        }
    ]
}