{
    "schemaVersion": 2,
    "mediaType": "application/vnd.docker.distribution.manifest.v2+json",
    "config": {
        "mediaType": "application/vnd.docker.container.image.v1+json",
        "size": 2299,
        "digest": "sha256:26117f899fdba1d100e4ecb4439119917f958974b12e862f63b21f54ad71fd30"
    },
    "layers": [
        {
            "mediaType": "application/vnd.docker.image.rootfs.diff.tar.gzip",
            "size": 140263,
            "digest": "sha256:bd104c018eeba582107400ed4b0ae7080a1ebe274cfac73f1cc1951c3238aa8b"
        },
        {
            "mediaType": "application/vnd.docker.image.rootfs.diff.tar.gzip",
            "size": 31007389,
            "digest": "sha256:0c1fad61523e4d7ab41cf2343ad3f0bffbd252e6774b3d83aa4389bd9c6ac762"
        },
        {
            "mediaType": "application/vnd.docker.image.rootfs.diff.tar.gzip",
            "size": 119776,
            "digest": "sha256:7206c93923be027022d65d6992b87d507200e02d5b4d8783f3518c4c30d43074"
        }
    ]
}