{
    "schemaVersion": 2,
    "mediaType": "application/vnd.docker.distribution.manifest.v2+json",
    "config": {
        "mediaType": "application/vnd.docker.container.image.v1+json",
        "size": 2162,
        "digest": "sha256:59e28bf2a416b509256592fd476464a4efcc9146181898e4244a3d0018d38805"
    },
    "layers": [
        {
            "mediaType": "application/vnd.docker.image.rootfs.diff.tar.gzip",
            "size": 140200,
            "digest": "sha256:cef3ecaf52732053cd4adad6840abcf67ed4f10082b5feddb6fc39c4df470005"
        },
        {
            "mediaType": "application/vnd.docker.image.rootfs.diff.tar.gzip",
            "size": 15989411,
            "digest": "sha256:58491b3f04d0753e6e4b4e63e484497c939e7d701ef36eb7d34bebb6035e01aa"
        }
    ]
}