{
    "schemaVersion": 2,
    "mediaType": "application/vnd.docker.distribution.manifest.v2+json",
    "config": {
        "mediaType": "application/vnd.docker.container.image.v1+json",
        "size": 2298,
        "digest": "sha256:0dcb04222728e2514c90438e88fbfb17a2e848466b113ab671684b840e60cd98"
    },
    "layers": [
        {
            "mediaType": "application/vnd.docker.image.rootfs.diff.tar.gzip",
            "size": 140264,
            "digest": "sha256:62883b870396ced70c6032e2c7091e26f07aa20d343b72c90b662cf6f77cb82b"
        },
        {
            "mediaType": "application/vnd.docker.image.rootfs.diff.tar.gzip",
            "size": 21763762,
            "digest": "sha256:d35dd99d3279b3085910f559d51996b65a82113591339d17577bd3f2fd93d452"
        },
        {
            "mediaType": "application/vnd.docker.image.rootfs.diff.tar.gzip",
            "size": 101964,
            "digest": "sha256:398aa50236432188667c7e76ec2408396b18e420ca317c4fe1a619532732bb54"
        }
    ]
}