{
    "schemaVersion": 2,
    "mediaType": "application/vnd.docker.distribution.manifest.v2+json",
    "config": {
        "mediaType": "application/vnd.docker.container.image.v1+json",
        "size": 2297,
        "digest": "sha256:32d38f04452959d3c9abdced0bfe38aa32287065b3d80803e488ff16b2ef4e56"
    },
    "layers": [
        {
            "mediaType": "application/vnd.docker.image.rootfs.diff.tar.gzip",
            "size": 140199,
            "digest": "sha256:f7f6a29e97548efbaa49ff85055f67410f3fa51d248ebc3e03367b6b043a0960"
        },
        {
            "mediaType": "application/vnd.docker.image.rootfs.diff.tar.gzip",
            "size": 16386727,
            "digest": "sha256:d23dd9c7b609621acb5a59118dc999d84adf1ffa3eb0b9eb7869e1aa9f391ebd"
        },
        {
            "mediaType": "application/vnd.docker.image.rootfs.diff.tar.gzip",
            "size": 98811,
            "digest": "sha256:ec6b67897833afe94d54edb0baa57a1344447945507303d0f64ad81fdce1a716"
        }
    ]
}