{
    "schemaVersion": 2,
    "mediaType": "application/vnd.docker.distribution.manifest.v2+json",
    "config": {
        "mediaType": "application/vnd.docker.container.image.v1+json",
        "size": 1778,
        "digest": "sha256:edeeff7abfaa0e64116f429a04232b8a9868a82a0496b7a0c6217cd90267a5d2"
    },
    "layers": [
        {
            "mediaType": "application/vnd.docker.image.rootfs.diff.tar.gzip",
            "size": 13055407,
            "digest": "sha256:b5b49726448471a5916674b00662ae59c415908317dbc724ec49ad78dd5634c6"
        },
        {
            "mediaType": "application/vnd.docker.image.rootfs.diff.tar.gzip",
            "size": 96990,
            "digest": "sha256:2147597527fa89f48798df5697bf670ac3c638a25e9fdb2822dbdd87076ff137"
        }
    ]
}