{
    "schemaVersion": 2,
    "mediaType": "application/vnd.docker.distribution.manifest.v2+json",
    "config": {
        "mediaType": "application/vnd.docker.container.image.v1+json",
        "size": 1748,
        "digest": "sha256:384fd59e7e0868c6a905e4f748e52dca1eba540d66cb11e3f7da4132965e8254"
    },
    "layers": [
        {
            "mediaType": "application/vnd.docker.image.rootfs.diff.tar.gzip",
            "size": 17120714,
            "digest": "sha256:5e5185d93c56c6019f42f9435eadaefd22d7e26c8059f5d6c695f23be4a5ca2f"
        },
        {
            "mediaType": "application/vnd.docker.image.rootfs.diff.tar.gzip",
            "size": 98807,
            "digest": "sha256:e09f5b5ba549f4b8b9cf5f12fad05d15b288538e59b803d049dadefb02970e22"
        }
    ]
}