{
    "schemaVersion": 2,
    "mediaType": "application/vnd.docker.distribution.manifest.v2+json",
    "config": {
        "mediaType": "application/vnd.docker.container.image.v1+json",
        "size": 1747,
        "digest": "sha256:552fdad3f75db6d728788405c882077cc60bc2fe77c4d04cb6d9d9d60ca64b88"
    },
    "layers": [
        {
            "mediaType": "application/vnd.docker.image.rootfs.diff.tar.gzip",
            "size": 17002586,
            "digest": "sha256:e42f945e42433798594a6dbc621db885ac10d7b5348aebc675304afbdcfbdaaf"
        },
        {
            "mediaType": "application/vnd.docker.image.rootfs.diff.tar.gzip",
            "size": 98816,
            "digest": "sha256:699900dae93293627f20d6d4c5fcd6ff5d2319cde354ca40d75868ec129f1e46"
        }
    ]
}