{
    "schemaVersion": 2,
    "mediaType": "application/vnd.docker.distribution.manifest.v2+json",
    "config": {
        "mediaType": "application/vnd.docker.container.image.v1+json",
        "size": 4793,
        "digest": "sha256:e7259faeda508c09c71f39a0c68a5f91a4c72cfef95890e52d08b0ee05d0657b"
    },
    "layers": [
        {
            "mediaType": "application/vnd.docker.image.rootfs.diff.tar.gzip",
            "size": 43767987,
            "digest": "sha256:9ff7e2e5f967fb9c4e8099e63508ab0dddebe3f820d08ca7fd568431b0d10c0e"
        },
        {
            "mediaType": "application/vnd.docker.image.rootfs.diff.tar.gzip",
            "size": 848,
            "digest": "sha256:59856638ac9f32d4caa0f5761b2597fe251642786fdfe1b917ddbb074b890c29"
        },
        {
            "mediaType": "application/vnd.docker.image.rootfs.diff.tar.gzip",
            "size": 526,
            "digest": "sha256:6f317d6d954b9a59c54b2cb09e1f30cd3e872796e431cd2ceac5ed570beb2939"
        },
        {
            "mediaType": "application/vnd.docker.image.rootfs.diff.tar.gzip",
            "size": 168,
            "digest": "sha256:a9dde5e2a643eca8fde0eed52f4aed31f3ecd9c1b2f24d5e3729cd8d2ae68177"
        },
        {
            "mediaType": "application/vnd.docker.image.rootfs.diff.tar.gzip",
            "size": 49796884,
            "digest": "sha256:61323d141c71d728aa153c9cf44bb232751422eebdbbc106cb446ea1ec36566d"
        },
        {
            "mediaType": "application/vnd.docker.image.rootfs.diff.tar.gzip",
            "size": 18301987,
            "digest": "sha256:73b8e061696087e0079b74365de886258b6edf7393f921dae69cebc0105304fc"
        },
        {
            "mediaType": "application/vnd.docker.image.rootfs.diff.tar.gzip",
            "size": 101747,
            "digest": "sha256:debcd6cfced74d346c36ec50f5866db62b9992b5baf7996391d0cd676e5610d1"
        }
    ]
}