{
    "schemaVersion": 2,
    "mediaType": "application/vnd.docker.distribution.manifest.list.v2+json",
    "manifests": [
        {
            "mediaType": "application/vnd.docker.distribution.manifest.v2+json",
            "size": 741,
            "digest": "sha256:65753766621dcad250ffa5b433ca87a4c3c6ffd86835e442e01114882bb3379b",
            "platform": {
                "architecture": "amd64",
                "os": "linux"
            }
        },
        {
            "mediaType": "application/vnd.docker.distribution.manifest.v2+json",
            "size": 741,
            "digest": "sha256:3a78db8bd65910459be42096fdffad9426d0335e72c38ecd3e21405a89f06a10",
            "platform": {
                "architecture": "arm",
                "os": "linux"
            }
        },
        {
            "mediaType": "application/vnd.docker.distribution.manifest.v2+json",
            "size": 741,
            "digest": "sha256:e02370b322095242dd260beace2145abf81724d3602a2b9b9a00c35959e2f931",
            "platform": {
                "architecture": "arm64",
                "os": "linux"
            }
        },
        {
            "mediaType": "application/vnd.docker.distribution.manifest.v2+json",
            "size": 741,
            "digest": "sha256:98c19c5db863a3674446e9798cc1b53cebbe84998d5b7ccb85a1934ee7b5e9bd",
            "platform": {
                "architecture": "ppc64le",
                "os": "linux"
            }
        },
        {
            "mediaType": "application/vnd.docker.distribution.manifest.v2+json",
            "size": 741,
            "digest": "sha256:7bda674c7b90516f18166491bcf41570a8e20d6590c8651b8b3fb7072fef96e4",
            "platform": {
                "architecture": "s390x",
                "os": "linux"
            }
        }
    ]
}