{
    "schemaVersion": 2,
    "mediaType": "application/vnd.docker.distribution.manifest.list.v2+json",
    "manifests": [
        {
            "mediaType": "application/vnd.docker.distribution.manifest.v2+json",
            "size": 741,
            "digest": "sha256:1f0bc33745abce5ac712373af03e9837b303b7a9c71aae522db74b54cd9aabe8",
            "platform": {
                "architecture": "amd64",
                "os": "linux"
            }
        },
        {
            "mediaType": "application/vnd.docker.distribution.manifest.v2+json",
            "size": 741,
            "digest": "sha256:e578ea1b9ee009484b185f64a9004bee067f393e474ef0cc2737e1df3d7a8b72",
            "platform": {
                "architecture": "arm",
                "os": "linux"
            }
        },
        {
            "mediaType": "application/vnd.docker.distribution.manifest.v2+json",
            "size": 741,
            "digest": "sha256:70d1d1a8f1179884a0a2cdfef3a1a2f77cca325cb99d1a0b7e76954d1960125a",
            "platform": {
                "architecture": "arm64",
                "os": "linux"
            }
        },
        {
            "mediaType": "application/vnd.docker.distribution.manifest.v2+json",
            "size": 741,
            "digest": "sha256:ff3e42a03a2adadc27dc0610d7061f0a3ce17d6a868d65dc3929689e47d71864",
            "platform": {
                "architecture": "ppc64le",
                "os": "linux"
            }
        },
        {
            "mediaType": "application/vnd.docker.distribution.manifest.v2+json",
            "size": 741,
            "digest": "sha256:c4439159cea09ec890ceea0bd1f2b49938f687b42f20794712f8c74488cc9057",
            "platform": {
                "architecture": "s390x",
                "os": "linux"
            }
        }
    ]
}