{
    "schemaVersion": 2,
    "mediaType": "application/vnd.docker.distribution.manifest.list.v2+json",
    "manifests": [
        {
            "mediaType": "application/vnd.docker.distribution.manifest.v2+json",
            "size": 741,
            "digest": "sha256:2b2efb303b9672fcd45cbec7e4a84404599daf960dc4b295dfcfebcd4ddb56ff",
            "platform": {
                "architecture": "amd64",
                "os": "linux"
            }
        },
        {
            "mediaType": "application/vnd.docker.distribution.manifest.v2+json",
            "size": 741,
            "digest": "sha256:1b368c7051a5ae0051b00da60377d90e0f4fd7aa0faa9a4ba81ffabb9f91dee2",
            "platform": {
                "architecture": "arm",
                "os": "linux"
            }
        },
        {
            "mediaType": "application/vnd.docker.distribution.manifest.v2+json",
            "size": 741,
            "digest": "sha256:201f63f24e6ac3d2227875d9e67af2adfc7b71051429270f5b0aa4e3b332ca7b",
            "platform": {
                "architecture": "arm64",
                "os": "linux"
            }
        },
        {
            "mediaType": "application/vnd.docker.distribution.manifest.v2+json",
            "size": 741,
            "digest": "sha256:99b5d3b92742e7ea946fd86984a56888d4e10a0b4c25bbde90f28bbb07eb02b4",
            "platform": {
                "architecture": "ppc64le",
                "os": "linux"
            }
        },
        {
            "mediaType": "application/vnd.docker.distribution.manifest.v2+json",
            "size": 741,
            "digest": "sha256:a2593dca4dccd52f146889dc2b857df3a9a2af90fe3f33ced7080458915d078a",
            "platform": {
                "architecture": "s390x",
                "os": "linux"
            }
        }
    ]
}