{
    "schemaVersion": 2,
    "mediaType": "application/vnd.docker.distribution.manifest.v2+json",
    "config": {
        "mediaType": "application/vnd.docker.container.image.v1+json",
        "size": 5253,
        "digest": "sha256:8b9d8f507824e5cb4f885fa7be0a57db1d9ad67b5d5c4bc8869c10aa4121b074"
    },
    "layers": [
        {
            "mediaType": "application/vnd.docker.image.rootfs.diff.tar.gzip",
            "size": 26687415,
            "digest": "sha256:35c102085707f703de2d9eaad8752d6fe1b8f02b5d2149f1d8357c9cc7fb7d0a"
        },
        {
            "mediaType": "application/vnd.docker.image.rootfs.diff.tar.gzip",
            "size": 35366,
            "digest": "sha256:251f5509d51d9e4119d4ffb70d4820f8e2d7dc72ad15df3ebd7cd755539e40fd"
        },
        {
            "mediaType": "application/vnd.docker.image.rootfs.diff.tar.gzip",
            "size": 848,
            "digest": "sha256:8e829fe70a46e3ac4334823560e98b257234c23629f19f05460e21a453091e6d"
        },
        {
            "mediaType": "application/vnd.docker.image.rootfs.diff.tar.gzip",
            "size": 162,
            "digest": "sha256:6001e1789921cf851f6fb2e5fe05be70f482fe9c2286f66892fe5a3bc404569c"
        },
        {
            "mediaType": "application/vnd.docker.image.rootfs.diff.tar.gzip",
            "size": 14897096,
            "digest": "sha256:8a881692a28f51a73ab3c528da71edcdc4847c568fcf350632085638647e6e5b"
        },
        {
            "mediaType": "application/vnd.docker.image.rootfs.diff.tar.gzip",
            "size": 1362,
            "digest": "sha256:a0c595fff040648498da13e5ec253cd60d444ca8e2795fdb782b2ce4278e776a"
        },
        {
            "mediaType": "application/vnd.docker.image.rootfs.diff.tar.gzip",
            "size": 51653621,
            "digest": "sha256:3e81b8be0d38852fc073ecdf29a90e636a104e00e5d8117c793ad50bb3695e63"
        },
        {
            "mediaType": "application/vnd.docker.image.rootfs.diff.tar.gzip",
            "size": 14900136,
            "digest": "sha256:68f1f7dcd346f883b0b7f6329a14cb49438bf0c5132caa7a479dea1a49d37c99"
        }
    ]
}