{
    "schemaVersion": 2,
    "mediaType": "application/vnd.docker.distribution.manifest.v2+json",
    "config": {
        "mediaType": "application/vnd.docker.container.image.v1+json",
        "size": 1785,
        "digest": "sha256:1e9db3651ba66257c5e963fa56e4c55d4e4d20ef2796c212e5ed5e5cb4c3ee78"
    },
    "layers": [
        {
            "mediaType": "application/vnd.docker.image.rootfs.diff.tar.gzip",
            "size": 4068,
            "digest": "sha256:986e41799796a22342b97265078bb17ef6a41fdeb80e490015f5716b6db315cb"
        },
        {
            "mediaType": "application/vnd.docker.image.rootfs.diff.tar.gzip",
            "size": 32619582,
            "digest": "sha256:272e56bc8dc5dcf83c90812e01cbdc80defceb189354d40f441bf882e2a6f072"
        }
    ]
}