{
    "schemaVersion": 2,
    "mediaType": "application/vnd.docker.distribution.manifest.v2+json",
    "config": {
        "mediaType": "application/vnd.docker.container.image.v1+json",
        "size": 5939,
        "digest": "sha256:afb3e5488873bfe5f209ba94f3415f09ac90d2a3279674310f6a5084233dcb44"
    },
    "layers": [
        {
            "mediaType": "application/vnd.docker.image.rootfs.diff.tar.gzip",
            "size": 2206542,
            "digest": "sha256:8e3ba11ec2a2b39ab372c60c16b421536e50e5ce64a0bc81765c2e38381bcff6"
        },
        {
            "mediaType": "application/vnd.docker.image.rootfs.diff.tar.gzip",
            "size": 239,
            "digest": "sha256:311ad0da45338842480bf25c6e6b7bb133b7b8cf709c3470db171ec370da5539"
        },
        {
            "mediaType": "application/vnd.docker.image.rootfs.diff.tar.gzip",
            "size": 54798327,
            "digest": "sha256:391a6a6b36513d84d55cbbe7e13bca7e92fbf257d910a5255f2b7bc9fcff4edf"
        },
        {
            "mediaType": "application/vnd.docker.image.rootfs.diff.tar.gzip",
            "size": 201334941,
            "digest": "sha256:4bd67bcc05e291c2b6e982422507f6fa38b496027006570cf6fb7617adb701db"
        },
        {
            "mediaType": "application/vnd.docker.image.rootfs.diff.tar.gzip",
            "size": 58316875,
            "digest": "sha256:eeb08d0f19106c1517f4ce35af88da866408b2f9b6f53f1c8a1ff09fea28e389"
        },
        {
            "mediaType": "application/vnd.docker.image.rootfs.diff.tar.gzip",
            "size": 14039715,
            "digest": "sha256:8b0c67d9d602253621969cc77f075d2d04a27d21ae25b59284656fe13e900a3d"
        },
        {
            "mediaType": "application/vnd.docker.image.rootfs.diff.tar.gzip",
            "size": 1259,
            "digest": "sha256:b32d0b58c5fd93352717e437404a59169f91a4f620cdc86d28f9788c86f53766"
        }
    ]
}