{
    "schemaVersion": 2,
    "mediaType": "application/vnd.docker.distribution.manifest.v2+json",
    "config": {
        "mediaType": "application/vnd.docker.container.image.v1+json",
        "size": 10540,
        "digest": "sha256:e183dc942c026c179ca8eab9f917ea10b6a6d001a314fcfdc7b4c337dd82aa7f"
    },
    "layers": [
        {
            "mediaType": "application/vnd.docker.image.rootfs.diff.tar.gzip",
            "size": 45339314,
            "digest": "sha256:c5e155d5a1d130a7f8a3e24cee0d9e1349bff13f90ec6a941478e558fde53c14"
        },
        {
            "mediaType": "application/vnd.docker.image.rootfs.diff.tar.gzip",
            "size": 10784878,
            "digest": "sha256:221d80d00ae9675aad24913aacbadfac1ce8b7084f9765a6c0813486082c5c69"
        },
        {
            "mediaType": "application/vnd.docker.image.rootfs.diff.tar.gzip",
            "size": 4340094,
            "digest": "sha256:4250b3117dca5e14edc32ebf1366cd54e4cda91f17610b76c504a86917ff8b95"
        },
        {
            "mediaType": "application/vnd.docker.image.rootfs.diff.tar.gzip",
            "size": 50066382,
            "digest": "sha256:3b7ca19181b24b87e24423c01b490633bc1e47d2fcdc1987bf2e37949d6789b5"
        },
        {
            "mediaType": "application/vnd.docker.image.rootfs.diff.tar.gzip",
            "size": 4932067,
            "digest": "sha256:acd9a038f588d8e2b2e3f146ed7adb7b6f8e373516efc24c78c8208f8812ad14"
        },
        {
            "mediaType": "application/vnd.docker.image.rootfs.diff.tar.gzip",
            "size": 222,
            "digest": "sha256:2aa7bd7991994877c85197911e3de5a0f6eecce76c0684b9d5eaf095aba2671a"
        },
        {
            "mediaType": "application/vnd.docker.image.rootfs.diff.tar.gzip",
            "size": 103993650,
            "digest": "sha256:47ce9f19f5673fe0e0749218052da4940d0c647485f1759ad8c5d3e79b3f7cf9"
        },
        {
            "mediaType": "application/vnd.docker.image.rootfs.diff.tar.gzip",
            "size": 720456201,
            "digest": "sha256:d164a6c6daf4afe0328d14d05827092e02b0909d13ae3ffa53fdf4b61ac4c33d"
        },
        {
            "mediaType": "application/vnd.docker.image.rootfs.diff.tar.gzip",
            "size": 238298878,
            "digest": "sha256:db0fd15bf4c9e65a514e72004282abac74ec88ead6837290de96474d726d5043"
        },
        {
            "mediaType": "application/vnd.docker.image.rootfs.diff.tar.gzip",
            "size": 252,
            "digest": "sha256:2f06229509616d8bcd288e9ab4aa632526909a472afaf2236c69c809f91792ef"
        },
        {
            "mediaType": "application/vnd.docker.image.rootfs.diff.tar.gzip",
            "size": 204,
            "digest": "sha256:79dd1019332026314e5a2b552f1fd81048e2fbfb68c147fd2b40c111bd3532f3"
        },
        {
            "mediaType": "application/vnd.docker.image.rootfs.diff.tar.gzip",
            "size": 14392162,
            "digest": "sha256:b31daa0b292aa024fdae11e4cab7353df7a512ed286dc7065a2690643155e504"
        },
        {
            "mediaType": "application/vnd.docker.image.rootfs.diff.tar.gzip",
            "size": 6985488,
            "digest": "sha256:f4a26389faa159a34142d051b4763b4a2e4613b0b0fc450935fec57943590884"
        },
        {
            "mediaType": "application/vnd.docker.image.rootfs.diff.tar.gzip",
            "size": 4203,
            "digest": "sha256:155f08816bccc41019d13f2a9b6ef22ac309686a6ab3cd171c628e79884db9dc"
        }
    ]
}