{
    "schemaVersion": 2,
    "mediaType": "application/vnd.docker.distribution.manifest.v2+json",
    "config": {
        "mediaType": "application/vnd.docker.container.image.v1+json",
        "size": 5948,
        "digest": "sha256:28004305a03acd43982da0f038e0c862a3fab20a9e0c1b885b243d8d471d67f4"
    },
    "layers": [
        {
            "mediaType": "application/vnd.docker.image.rootfs.diff.tar.gzip",
            "size": 2813316,
            "digest": "sha256:cbdbe7a5bc2a134ca8ec91be58565ec07d037386d1f1d8385412d224deafca08"
        },
        {
            "mediaType": "application/vnd.docker.image.rootfs.diff.tar.gzip",
            "size": 279222890,
            "digest": "sha256:8c6c04b2b3e9ee9b807efe6544f9b5cc3bad8ac1383f34d4d4bbe70e0f949470"
        },
        {
            "mediaType": "application/vnd.docker.image.rootfs.diff.tar.gzip",
            "size": 79118136,
            "digest": "sha256:1b30ac5b315077027eb55acc7cf3fe0f4629768adca9debc239648cd7bdf0548"
        },
        {
            "mediaType": "application/vnd.docker.image.rootfs.diff.tar.gzip",
            "size": 21842814,
            "digest": "sha256:16c4ed0ab3a69a8678fe4c646cb5806cd269ca7b234c2757e5eb528c7d729f0d"
        },
        {
            "mediaType": "application/vnd.docker.image.rootfs.diff.tar.gzip",
            "size": 87469,
            "digest": "sha256:96b9faf6e677608cab499a8f6898d37a2c0931be95c2224d6c0b10ccc83de528"
        },
        {
            "mediaType": "application/vnd.docker.image.rootfs.diff.tar.gzip",
            "size": 153,
            "digest": "sha256:b726d354f7b37bff9870a7c3e1e78790316daf8691e2d5a8c981bbd0b7b1567c"
        },
        {
            "mediaType": "application/vnd.docker.image.rootfs.diff.tar.gzip",
            "size": 192,
            "digest": "sha256:835dba6dbf6cf982f991211d5a1b144c51143d92e962d10344087bf22dfd3d2b"
        },
        {
            "mediaType": "application/vnd.docker.image.rootfs.diff.tar.gzip",
            "size": 13490081,
            "digest": "sha256:c8e0604ae68904803cf5b000f3fcc0a7e33139294e786c440cdc6a31a1a1ae37"
        },
        {
            "mediaType": "application/vnd.docker.image.rootfs.diff.tar.gzip",
            "size": 9416404,
            "digest": "sha256:c3a7330aa1479abccb231f40761f2afb30a5b77e99fb70e321b55c3303016eb6"
        },
        {
            "mediaType": "application/vnd.docker.image.rootfs.diff.tar.gzip",
            "size": 540,
            "digest": "sha256:ac8d18a134ccdb44a99989cf0c37610c6dc8403e53835cbd49a2825c97da5ea8"
        },
        {
            "mediaType": "application/vnd.docker.image.rootfs.diff.tar.gzip",
            "size": 1261,
            "digest": "sha256:9ff2a7fad9a5f775c2287cbbf534eac456c58f378999c79f097a1a485886df70"
        }
    ]
}