{
    "schemaVersion": 2,
    "mediaType": "application/vnd.docker.distribution.manifest.v2+json",
    "config": {
        "mediaType": "application/vnd.docker.container.image.v1+json",
        "size": 2973,
        "digest": "sha256:619702b68ca55b2513d1ab1bef932500cb285f6c10ac9580303a46018efa8f4e"
    },
    "layers": [
        {
            "mediaType": "application/vnd.docker.image.rootfs.diff.tar.gzip",
            "size": 27098756,
            "digest": "sha256:afb6ec6fdc1c3ba04f7a56db32c5ff5ff38962dc4cd0ffdef5beaa0ce2eb77e2"
        },
        {
            "mediaType": "application/vnd.docker.image.rootfs.diff.tar.gzip",
            "size": 666,
            "digest": "sha256:c4dd4ba90dfc037db6d1cfc097b3bd47b541c867bd50e127eb6a4ffd012d159a"
        },
        {
            "mediaType": "application/vnd.docker.image.rootfs.diff.tar.gzip",
            "size": 1081835,
            "digest": "sha256:8b70b4b8acfda3256acf26630977773118646c57bca984431ce82250419c08b6"
        },
        {
            "mediaType": "application/vnd.docker.image.rootfs.diff.tar.gzip",
            "size": 1300,
            "digest": "sha256:a78738ecb5ab0612669c952af6544bc6152472d1b3ab2529e81ae4f89aceec25"
        },
        {
            "mediaType": "application/vnd.docker.image.rootfs.diff.tar.gzip",
            "size": 19484659,
            "digest": "sha256:da868b7f25e409c35cf93232826077a9ad403eb5eed9afecdb47ffc40334a11e"
        },
        {
            "mediaType": "application/vnd.docker.image.rootfs.diff.tar.gzip",
            "size": 4701,
            "digest": "sha256:12245c060cf9686453e5a2cc6d95956098f64d5605827de588d39e1e515e38c5"
        },
        {
            "mediaType": "application/vnd.docker.image.rootfs.diff.tar.gzip",
            "size": 4089,
            "digest": "sha256:f1bac3b27495a926ce1b9968af80571f901d5515a2ab2b014c1c1ca4d3d7db40"
        },
        {
            "mediaType": "application/vnd.docker.image.rootfs.diff.tar.gzip",
            "size": 1023,
            "digest": "sha256:db43a924afae0a1da2a9e4fb9d117a0209b9bc73149478ce8b58189219395aeb"
        },
        {
            "mediaType": "application/vnd.docker.image.rootfs.diff.tar.gzip",
            "size": 901,
            "digest": "sha256:a2ef7dcb6403189e49770fd08d51cdc08476c4318bbbc9ea22142ca7ff064aec"
        }
    ]
}