{
    "schemaVersion": 2,
    "mediaType": "application/vnd.docker.distribution.manifest.v2+json",
    "config": {
        "mediaType": "application/vnd.docker.container.image.v1+json",
        "size": 3775,
        "digest": "sha256:62999832562f6c7b33269fad93be9a7138409c9e94c6b9c3f7576807646920e0"
    },
    "layers": [
        {
            "mediaType": "application/vnd.docker.image.rootfs.diff.tar.gzip",
            "size": 22517431,
            "digest": "sha256:9fc222b64b0a005c742f1b50f03986a7f768d41434994430718917d88fefe567"
        },
        {
            "mediaType": "application/vnd.docker.image.rootfs.diff.tar.gzip",
            "size": 33067719,
            "digest": "sha256:be3aa870369b5788d8979826eec750525796882114967487e04a3d279ea82256"
        },
        {
            "mediaType": "application/vnd.docker.image.rootfs.diff.tar.gzip",
            "size": 102,
            "digest": "sha256:e5af61df5e9757b555339566495c87354b25c4e49248b3bdeebb50892d641876"
        },
        {
            "mediaType": "application/vnd.docker.image.rootfs.diff.tar.gzip",
            "size": 1739908,
            "digest": "sha256:20013f80d2d46e79f86dbcfe19bafe158e770f9f0779f6ad51d8a04cadf2efcb"
        },
        {
            "mediaType": "application/vnd.docker.image.rootfs.diff.tar.gzip",
            "size": 18705083,
            "digest": "sha256:abd38327b1feacaab400697df9a3d86ef02c6e77c73b1eece87bb8e801ca9673"
        },
        {
            "mediaType": "application/vnd.docker.image.rootfs.diff.tar.gzip",
            "size": 4071,
            "digest": "sha256:2789040f14b227fa75e2ba05c907920791f0fead2bbafe670e2588c609540661"
        },
        {
            "mediaType": "application/vnd.docker.image.rootfs.diff.tar.gzip",
            "size": 3462,
            "digest": "sha256:6116ecf24f81cef3b3a94d3158b2c41678ba066db704e6269b97f9b8e2095a03"
        },
        {
            "mediaType": "application/vnd.docker.image.rootfs.diff.tar.gzip",
            "size": 455,
            "digest": "sha256:c2ae0683f3f1151ca75d59d164eccc099b07779ddf4d27f80d7a2276935acb6a"
        },
        {
            "mediaType": "application/vnd.docker.image.rootfs.diff.tar.gzip",
            "size": 340,
            "digest": "sha256:e89ea22452c2ada47877e3a643bd69cb6e33d46e1f523b972f012a213f35c791"
        }
    ]
}