{
    "schemaVersion": 2,
    "mediaType": "application/vnd.docker.distribution.manifest.v2+json",
    "config": {
        "mediaType": "application/vnd.docker.container.image.v1+json",
        "size": 5948,
        "digest": "sha256:60a6bdc15c9e4700be6d4f6d38ac33f721e6d92849507deb68b7b1d22b1e1564"
    },
    "layers": [
        {
            "mediaType": "application/vnd.docker.image.rootfs.diff.tar.gzip",
            "size": 44149770,
            "digest": "sha256:0a01a72a686c389637334de1e2d0012da298960366f6d8f358b8e10dc3b5e330"
        },
        {
            "mediaType": "application/vnd.docker.image.rootfs.diff.tar.gzip",
            "size": 525,
            "digest": "sha256:cc899a5544da1a6cfb970d2484d32c063f8df26a430d92f39c98e72261e226f2"
        },
        {
            "mediaType": "application/vnd.docker.image.rootfs.diff.tar.gzip",
            "size": 844,
            "digest": "sha256:19197c55075519928dd2ff059745665a2c9b72f4e8af6f7a1ce662e696d339bd"
        },
        {
            "mediaType": "application/vnd.docker.image.rootfs.diff.tar.gzip",
            "size": 168,
            "digest": "sha256:716d454e56b61d1343a01f3b1829574333e2e3df20e77d1958d7b0b939ea1b61"
        },
        {
            "mediaType": "application/vnd.docker.image.rootfs.diff.tar.gzip",
            "size": 484497,
            "digest": "sha256:14a11205c793e6af55c529d0ccd31a29ecf1b1c661ea5743c1bffaff2e46e1b6"
        },
        {
            "mediaType": "application/vnd.docker.image.rootfs.diff.tar.gzip",
            "size": 13809193,
            "digest": "sha256:ad3548670fda787c6143ce9b35c4b59e31c196eb6754c9e44065ce5eb7de5c15"
        },
        {
            "mediaType": "application/vnd.docker.image.rootfs.diff.tar.gzip",
            "size": 6340,
            "digest": "sha256:50a4bb9cb5d321eb61a6744ccf771ce91dd001001e0b549eb01c0346ed2d8e0b"
        },
        {
            "mediaType": "application/vnd.docker.image.rootfs.diff.tar.gzip",
            "size": 3713,
            "digest": "sha256:3293068a150450052852e81d57261a2c4c79704ebdaa45db844555a3bd3bba84"
        },
        {
            "mediaType": "application/vnd.docker.image.rootfs.diff.tar.gzip",
            "size": 297,
            "digest": "sha256:01c8c1a4251ee3b5316d904353e20ad72e05df7d2058042cb95e43e2c4e9d2c1"
        },
        {
            "mediaType": "application/vnd.docker.image.rootfs.diff.tar.gzip",
            "size": 324,
            "digest": "sha256:41f121cf8cb64499a7b0e83eb6e404bb5c44595069f3501ef62a8bc3ccb80f6d"
        },
        {
            "mediaType": "application/vnd.docker.image.rootfs.diff.tar.gzip",
            "size": 119200,
            "digest": "sha256:9b3c5964cd9b07aa4bc00f44e0256f180b91a06b77a2d8cc2d399cc2f029dc7e"
        }
    ]
}