{
    "schemaVersion": 2,
    "mediaType": "application/vnd.docker.distribution.manifest.v2+json",
    "config": {
        "mediaType": "application/vnd.docker.container.image.v1+json",
        "size": 1601,
        "digest": "sha256:4fbda970f589293a0f1798efe6323a5664e06a65b92480c639ca4cfe988a58ca"
    },
    "layers": [
        {
            "mediaType": "application/vnd.docker.image.rootfs.diff.tar.gzip",
            "size": 9769276,
            "digest": "sha256:852f90ccfee81b4b46e2b9eed78d51647cf5ce82c8081443114c43ce535d3f5a"
        }
    ]
}