{
    "schemaVersion": 2,
    "mediaType": "application/vnd.docker.distribution.manifest.v2+json",
    "config": {
        "mediaType": "application/vnd.docker.container.image.v1+json",
        "size": 2008,
        "digest": "sha256:1577128c0502f8620d3c04e8118ddc0390d9613dfa9faf398010e883ddcec16f"
    },
    "layers": [
        {
            "mediaType": "application/vnd.docker.image.rootfs.diff.tar.gzip",
            "size": 655317,
            "digest": "sha256:9ff2acc3204b4093126adab3fed72de8f7bbfe332255b199c30b8b185fcf6923"
        },
        {
            "mediaType": "application/vnd.docker.image.rootfs.diff.tar.gzip",
            "size": 10044222,
            "digest": "sha256:d68d37b580fc0d08a87f517b6fe0e7262f06db79b476d1fd90a20775041322e6"
        },
        {
            "mediaType": "application/vnd.docker.image.rootfs.diff.tar.gzip",
            "size": 119200,
            "digest": "sha256:b59174f3552916f6809890ec1c48d659bba59cbe310da6651d807edda3d4d9ae"
        }
    ]
}